LICENSE
MANIFEST.in
README.md
VERSION
setup.cfg
setup.py
src/cltl.entity_linking.egg-info/PKG-INFO
src/cltl.entity_linking.egg-info/SOURCES.txt
src/cltl.entity_linking.egg-info/dependency_links.txt
src/cltl.entity_linking.egg-info/requires.txt
src/cltl.entity_linking.egg-info/top_level.txt
src/cltl/entity_linking/__init__.py
src/cltl/entity_linking/api.py
src/cltl/entity_linking/deixis_linker.py
src/cltl/entity_linking/entity_querying.py
src/cltl/entity_linking/face_linker.py
src/cltl/entity_linking/label_linker.py
src/cltl/entity_linking/linkers.py
src/cltl/entity_linking/queries/face.rq
src/cltl/entity_linking/queries/popularity.rq
src/cltl/entity_linking/queries/popularity_label.rq
src/cltl/entity_linking/queries/recency_last_mention.rq
src/cltl/entity_linking/queries/recency_last_mention_label.rq
src/cltl_service/entity_linking/__init__.py
src/cltl_service/entity_linking/leolani.py
src/cltl_service/entity_linking/service.py