Metadata-Version: 2.1
Name: cltl.entity-linking
Version: 0.0.dev1
Summary: The Leolani Language module for identifying instances
Home-page: https://github.com/leolani/cltl-knowledgelinking
License: MIT License
Requires-Python: >=3.7
License-File: LICENSE
Requires-Dist: cltl.brain
Requires-Dist: jellyfish
Provides-Extra: service
Requires-Dist: cltl.combot; extra == "service"
